mqttwarn_contrib
